{"v":"4.8.0","meta":{"g":"LottieFiles AE 3.4.5","a":"","k":"","d":"","tc":""},"fr":25,"ip":0,"op":57,"w":2000,"h":2000,"nm":"Ball Throw","ddd":0,"assets":[],"layers":[{"ddd":0,"ind":1,"ty":3,"nm":"All Ctrl","sr":1,"ks":{"o":{"a":0,"k":0,"ix":11},"r":{"a":1,"k":[{"i":{"x":[0.708],"y":[1]},"o":{"x":[0.136],"y":[0]},"t":10,"s":[0]},{"i":{"x":[0.246],"y":[0.976]},"o":{"x":[0.887],"y":[0.704]},"t":20,"s":[31]},{"i":{"x":[0.246],"y":[2.501]},"o":{"x":[0.222],"y":[0]},"t":28,"s":[-10]},{"i":{"x":[0.21],"y":[1]},"o":{"x":[0.222],"y":[0]},"t":40,"s":[-10]},{"t":51,"s":[0]}],"ix":10},"p":{"a":1,"k":[{"i":{"x":0.708,"y":1},"o":{"x":0.136,"y":0},"t":10,"s":[471.735,1380.355,0],"to":[0,0,0],"ti":[0,0,0]},{"i":{"x":0.246,"y":0.978},"o":{"x":0.887,"y":0.623},"t":20,"s":[471.735,1503.525,0],"to":[0,0,0],"ti":[0,0,0]},{"i":{"x":0.246,"y":0.246},"o":{"x":0.222,"y":0.222},"t":28,"s":[471.735,1380.355,0],"to":[0,0,0],"ti":[0,0,0]},{"i":{"x":0.21,"y":0.21},"o":{"x":0.222,"y":0.222},"t":40,"s":[471.735,1380.355,0],"to":[0,0,0],"ti":[0,0,0]},{"t":51,"s":[471.735,1380.355,0]}],"ix":2},"a":{"a":0,"k":[60,60,0],"ix":1},"s":{"a":0,"k":[90.4,90.4,100],"ix":6}},"ao":0,"ip":0,"op":57,"st":0,"bm":0},{"ddd":0,"ind":2,"ty":3,"nm":"Hand Ctrl","parent":1,"sr":1,"ks":{"o":{"a":0,"k":0,"ix":11},"r":{"a":0,"k":0,"ix":10},"p":{"a":1,"k":[{"i":{"x":0.308,"y":1},"o":{"x":0.877,"y":0},"t":21,"s":[199,93,0],"to":[0,0,0],"ti":[0,0,0]},{"i":{"x":0.21,"y":1},"o":{"x":0.79,"y":0},"t":38,"s":[199,48,0],"to":[0,0,0],"ti":[0,0,0]},{"t":45,"s":[199,93,0]}],"ix":2},"a":{"a":0,"k":[60,60,0],"ix":1},"s":{"a":0,"k":[100,100,100],"ix":6}},"ao":0,"ip":0,"op":57,"st":0,"bm":0},{"ddd":0,"ind":3,"ty":4,"nm":"Pinky Fin 2","parent":2,"sr":1,"ks":{"o":{"a":0,"k":100,"ix":11},"r":{"a":0,"k":0,"ix":10},"p":{"a":0,"k":[298.833,59.06,0],"ix":2},"a":{"a":0,"k":[0,0,0],"ix":1},"s":{"a":0,"k":[100,100,100],"ix":6}},"ao":0,"shapes":[{"ty":"gr","it":[{"ind":0,"ty":"sh","ix":1,"ks":{"a":1,"k":[{"i":{"x":0.4,"y":1},"o":{"x":0.6,"y":0},"t":7,"s":[{"i":[[62.855,102.724],[-73.21,-11.2],[-30.324,-1.459],[-15.663,35.121],[-25.005,-18.779],[20.357,-39.783],[101.469,-21.3]],"o":[[-39.158,-74.991],[73.21,11.2],[30.324,1.459],[15.663,-35.121],[25.005,18.779],[-20.357,39.783],[-101.469,21.3]],"v":[[-222.701,29.391],[-89.628,-81.881],[40.735,-20.165],[131.691,-110.911],[212.868,-127.813],[216.216,-26.657],[37.341,132.726]],"c":true}]},{"i":{"x":0.4,"y":1},"o":{"x":0.6,"y":0},"t":21,"s":[{"i":[[62.855,102.724],[-73.21,-11.2],[-28.117,-11.451],[-38.074,5.397],[2.618,-31.161],[42.943,-12.37],[93.72,-4.68]],"o":[[-39.158,-74.991],[73.21,11.2],[28.117,11.451],[38.074,-5.397],[-2.618,31.161],[-42.917,12.362],[-103.552,5.171]],"v":[[-222.701,29.391],[-89.628,-81.881],[70.195,2.429],[231.427,7.306],[288.887,67.088],[204.978,123.684],[23.341,140.726]],"c":true}]},{"i":{"x":0.833,"y":0.833},"o":{"x":0.6,"y":0},"t":28,"s":[{"i":[[62.855,102.724],[-73.21,-11.2],[-29.813,-5.732],[-37.945,6.24],[1.927,-31.212],[42.658,-13.318],[92.56,-1.474]],"o":[[-39.158,-74.991],[73.21,11.2],[29.813,5.732],[37.945,-6.24],[-1.927,31.212],[-42.633,13.31],[-103.667,1.651]],"v":[[-222.701,29.391],[-89.628,-81.881],[42.576,-5.217],[227.472,-1.097],[286.242,57.397],[203.609,115.838],[23.668,139.573]],"c":true}]},{"i":{"x":0.4,"y":1},"o":{"x":0.167,"y":0.167},"t":37,"s":[{"i":[[62.855,102.724],[-73.21,-11.2],[-26.601,-14.38],[-38.287,-3.566],[9.763,-29.706],[44.638,-2.089],[87.124,18.038]],"o":[[-39.158,-74.991],[73.21,11.2],[26.601,14.38],[38.287,3.566],[-9.763,29.706],[-44.611,2.088],[-101.516,-21.017]],"v":[[-222.701,29.391],[-89.628,-81.881],[84.186,12.251],[255.733,60.44],[297.785,131.9],[203.057,167.525],[-2.173,150.594]],"c":true}]},{"t":43,"s":[{"i":[[62.855,102.724],[-73.21,-11.2],[-30.324,-1.459],[-15.663,35.121],[-25.005,-18.779],[20.357,-39.783],[101.469,-21.3]],"o":[[-39.158,-74.991],[73.21,11.2],[30.324,1.459],[15.663,-35.121],[25.005,18.779],[-20.357,39.783],[-101.469,21.3]],"v":[[-222.701,29.391],[-89.628,-81.881],[40.735,-20.165],[131.691,-110.911],[212.868,-127.813],[216.216,-26.657],[37.341,132.726]],"c":true}]}],"ix":2},"nm":"Path 1","mn":"ADBE Vector Shape - Group","hd":false},{"ty":"tm","s":{"a":0,"k":15,"ix":1},"e":{"a":0,"k":100,"ix":2},"o":{"a":0,"k":0,"ix":3},"m":1,"ix":2,"nm":"Trim Paths 1","mn":"ADBE Vector Filter - Trim","hd":false},{"ty":"st","c":{"a":0,"k":[0.317647069693,0.180392161012,0.113725490868,1],"ix":3},"o":{"a":0,"k":100,"ix":4},"w":{"a":0,"k":5,"ix":5},"lc":2,"lj":1,"ml":10,"bm":0,"nm":"Stroke 1","mn":"ADBE Vector Graphic - Stroke","hd":false},{"ty":"tr","p":{"a":0,"k":[0,0],"ix":2},"a":{"a":0,"k":[0,0],"ix":1},"s":{"a":0,"k":[100,100],"ix":3},"r":{"a":0,"k":0,"ix":6},"o":{"a":0,"k":100,"ix":7},"sk":{"a":0,"k":0,"ix":4},"sa":{"a":0,"k":0,"ix":5},"nm":"Transform"}],"nm":"Group 1","np":4,"cix":2,"bm":0,"ix":1,"mn":"ADBE Vector Group","hd":false}],"ip":0,"op":57,"st":0,"bm":0},{"ddd":0,"ind":4,"ty":4,"nm":"Pinky Fin","parent":2,"sr":1,"ks":{"o":{"a":0,"k":100,"ix":11},"r":{"a":0,"k":0,"ix":10},"p":{"a":0,"k":[299.939,57.954,0],"ix":2},"a":{"a":0,"k":[0,0,0],"ix":1},"s":{"a":0,"k":[100,100,100],"ix":6}},"ao":0,"shapes":[{"ty":"gr","it":[{"ind":0,"ty":"sh","ix":1,"ks":{"a":1,"k":[{"i":{"x":0.4,"y":1},"o":{"x":0.6,"y":0},"t":7,"s":[{"i":[[62.855,102.724],[-73.21,-11.2],[-30.324,-1.459],[-15.663,35.121],[-25.005,-18.779],[20.357,-39.783],[101.469,-21.3]],"o":[[-39.158,-74.991],[73.21,11.2],[30.324,1.459],[15.663,-35.121],[25.005,18.779],[-20.357,39.783],[-101.469,21.3]],"v":[[-222.701,29.391],[-89.628,-81.881],[40.735,-20.165],[131.691,-110.911],[212.868,-127.813],[216.216,-26.657],[37.341,132.726]],"c":true}]},{"i":{"x":0.4,"y":1},"o":{"x":0.6,"y":0},"t":21,"s":[{"i":[[62.855,102.724],[-73.21,-11.2],[-28.117,-11.451],[-38.074,5.397],[2.618,-31.161],[42.943,-12.37],[93.72,-4.68]],"o":[[-39.158,-74.991],[73.21,11.2],[28.117,11.451],[38.074,-5.397],[-2.618,31.161],[-42.917,12.362],[-103.552,5.171]],"v":[[-222.701,29.391],[-89.628,-81.881],[70.195,2.429],[231.427,7.306],[288.887,67.088],[204.978,123.684],[23.341,140.726]],"c":true}]},{"i":{"x":0.833,"y":0.833},"o":{"x":0.6,"y":0},"t":28,"s":[{"i":[[62.855,102.724],[-73.21,-11.2],[-29.813,-5.732],[-37.945,6.24],[1.927,-31.212],[42.658,-13.318],[92.56,-1.474]],"o":[[-39.158,-74.991],[73.21,11.2],[29.813,5.732],[37.945,-6.24],[-1.927,31.212],[-42.633,13.31],[-103.667,1.651]],"v":[[-222.701,29.391],[-89.628,-81.881],[42.576,-5.217],[227.472,-1.097],[286.242,57.397],[203.609,115.838],[23.668,139.573]],"c":true}]},{"i":{"x":0.4,"y":1},"o":{"x":0.167,"y":0.167},"t":37,"s":[{"i":[[62.855,102.724],[-73.21,-11.2],[-26.601,-14.38],[-38.287,-3.566],[9.763,-29.706],[44.638,-2.089],[87.124,18.038]],"o":[[-39.158,-74.991],[73.21,11.2],[26.601,14.38],[38.287,3.566],[-9.763,29.706],[-44.611,2.088],[-101.516,-21.017]],"v":[[-222.701,29.391],[-89.628,-81.881],[84.186,12.251],[255.733,60.44],[297.785,131.9],[203.057,167.525],[-2.173,150.594]],"c":true}]},{"t":43,"s":[{"i":[[62.855,102.724],[-73.21,-11.2],[-30.324,-1.459],[-15.663,35.121],[-25.005,-18.779],[20.357,-39.783],[101.469,-21.3]],"o":[[-39.158,-74.991],[73.21,11.2],[30.324,1.459],[15.663,-35.121],[25.005,18.779],[-20.357,39.783],[-101.469,21.3]],"v":[[-222.701,29.391],[-89.628,-81.881],[40.735,-20.165],[131.691,-110.911],[212.868,-127.813],[216.216,-26.657],[37.341,132.726]],"c":true}]}],"ix":2},"nm":"Path 1","mn":"ADBE Vector Shape - Group","hd":false},{"ty":"fl","c":{"a":0,"k":[0.600000023842,0.372549027205,0.247058823705,1],"ix":4},"o":{"a":0,"k":100,"ix":5},"r":1,"bm":0,"nm":"Fill 1","mn":"ADBE Vector Graphic - Fill","hd":false},{"ty":"tr","p":{"a":0,"k":[0,0],"ix":2},"a":{"a":0,"k":[0,0],"ix":1},"s":{"a":0,"k":[100,100],"ix":3},"r":{"a":0,"k":0,"ix":6},"o":{"a":0,"k":100,"ix":7},"sk":{"a":0,"k":0,"ix":4},"sa":{"a":0,"k":0,"ix":5},"nm":"Transform"}],"nm":"Group 1","np":3,"cix":2,"bm":0,"ix":1,"mn":"ADBE Vector Group","hd":false}],"ip":0,"op":57,"st":0,"bm":0},{"ddd":0,"ind":5,"ty":4,"nm":"RIng Fin","parent":2,"sr":1,"ks":{"o":{"a":0,"k":100,"ix":11},"r":{"a":0,"k":0,"ix":10},"p":{"a":0,"k":[472.003,39.906,0],"ix":2},"a":{"a":0,"k":[0,0,0],"ix":1},"s":{"a":0,"k":[100,100,100],"ix":6}},"ao":0,"shapes":[{"ty":"gr","it":[{"ind":0,"ty":"sh","ix":1,"ks":{"a":1,"k":[{"i":{"x":0.4,"y":1},"o":{"x":0.6,"y":0},"t":10,"s":[{"i":[[-68.627,-14.844],[6.33,-46.628],[59.495,-39.032],[32.269,2.803],[-112.926,-0.758],[-26.1,35.64]],"o":[[27.97,6.05],[-7.21,53.111],[-47.274,31.014],[-32.269,-2.803],[112.926,0.758],[41.04,-56.041]],"v":[[159.446,-155.503],[198.54,-75.19],[79.976,119.589],[-177.804,156.809],[-108.361,40.768],[57.857,-33.549]],"c":true}]},{"i":{"x":0.4,"y":1},"o":{"x":0.6,"y":0},"t":24,"s":[{"i":[[-39.559,-58.009],[36.69,-29.463],[70.655,-12.92],[31.294,8.356],[-111.085,-20.326],[-47.607,18.352]],"o":[[16.123,23.643],[-41.792,33.56],[-55.618,10.17],[-31.294,-8.356],[111.085,20.326],[64.812,-24.985]],"v":[[278.242,5.218],[251.311,90.384],[63.342,159.014],[-196.986,150.975],[-108.475,48.732],[120.604,23.742]],"c":true}]},{"i":{"x":0.833,"y":0.833},"o":{"x":0.6,"y":0},"t":28,"s":[{"i":[[-59.266,-37.651],[22.057,-41.565],[66.589,-26.925],[31.294,8.356],[-111.085,-20.326],[-36.477,35.674]],"o":[[24.155,15.345],[-25.124,47.345],[-52.417,21.194],[-31.294,-8.356],[111.085,20.326],[49.66,-48.567]],"v":[[209.529,-80.782],[218.452,8.093],[72.137,146.248],[-196.986,150.975],[-108.475,48.732],[72.048,-1.461]],"c":true}]},{"i":{"x":0.4,"y":1},"o":{"x":0.167,"y":0.167},"t":36,"s":[{"i":[[-49.413,-47.83],[29.374,-35.514],[68.622,-19.922],[31.294,8.356],[-111.085,-20.326],[-42.042,27.013]],"o":[[20.139,19.494],[-33.458,40.452],[-54.017,15.682],[-31.294,-8.356],[111.085,20.326],[57.236,-36.776]],"v":[[243.885,-37.782],[234.881,49.238],[67.74,152.631],[-196.986,150.975],[-108.475,48.732],[96.326,11.14]],"c":true}]},{"t":43,"s":[{"i":[[-68.627,-14.844],[6.33,-46.628],[59.495,-39.032],[32.269,2.803],[-112.926,-0.758],[-26.1,35.64]],"o":[[27.97,6.05],[-7.21,53.111],[-47.274,31.014],[-32.269,-2.803],[112.926,0.758],[41.04,-56.041]],"v":[[159.446,-155.503],[198.54,-75.19],[79.976,119.589],[-177.804,156.809],[-108.361,40.768],[57.857,-33.549]],"c":true}]}],"ix":2},"nm":"Path 1","mn":"ADBE Vector Shape - Group","hd":false},{"ty":"st","c":{"a":0,"k":[0.317647069693,0.180392161012,0.113725490868,1],"ix":3},"o":{"a":0,"k":100,"ix":4},"w":{"a":0,"k":5,"ix":5},"lc":2,"lj":1,"ml":10,"bm":0,"nm":"Stroke 1","mn":"ADBE Vector Graphic - Stroke","hd":false},{"ty":"fl","c":{"a":0,"k":[0.600000023842,0.372549027205,0.247058823705,1],"ix":4},"o":{"a":0,"k":100,"ix":5},"r":1,"bm":0,"nm":"Fill 1","mn":"ADBE Vector Graphic - Fill","hd":false},{"ty":"tr","p":{"a":0,"k":[0,0],"ix":2},"a":{"a":0,"k":[0,0],"ix":1},"s":{"a":0,"k":[100,100],"ix":3},"r":{"a":0,"k":0,"ix":6},"o":{"a":0,"k":100,"ix":7},"sk":{"a":0,"k":0,"ix":4},"sa":{"a":0,"k":0,"ix":5},"nm":"Transform"}],"nm":"Group 1","np":3,"cix":2,"bm":0,"ix":1,"mn":"ADBE Vector Group","hd":false}],"ip":0,"op":57,"st":0,"bm":0},{"ddd":0,"ind":6,"ty":4,"nm":"Ball","parent":1,"sr":1,"ks":{"o":{"a":0,"k":100,"ix":11},"r":{"a":0,"k":0,"ix":10},"p":{"a":1,"k":[{"i":{"x":0.79,"y":1},"o":{"x":0.341,"y":1},"t":23,"s":[572.429,-137.515,0],"to":[0,0,0],"ti":[61.469,5.929,0]},{"i":{"x":0.627,"y":0},"o":{"x":0.21,"y":0},"t":34,"s":[788.429,-1011.515,0],"to":[2.155,31.423,0],"ti":[198.19,-585.731,0]},{"t":44,"s":[572.429,-137.515,0]}],"ix":2},"a":{"a":0,"k":[0,0,0],"ix":1},"s":{"a":0,"k":[100,100,100],"ix":6}},"ao":0,"shapes":[{"ty":"gr","it":[{"ind":0,"ty":"sh","ix":1,"ks":{"a":0,"k":{"i":[[0,-152.313],[152.313,0],[0,152.313],[-152.313,0]],"o":[[0,152.313],[-152.313,0],[0,-152.313],[152.313,0]],"v":[[275.787,0],[0,275.787],[-275.787,0],[0,-275.787]],"c":true},"ix":2},"nm":"Path 1","mn":"ADBE Vector Shape - Group","hd":false},{"ty":"fl","c":{"a":0,"k":[0.093656278124,0.796078431373,0.325042455337,1],"ix":4},"o":{"a":0,"k":100,"ix":5},"r":1,"bm":0,"nm":"Fill 1","mn":"ADBE Vector Graphic - Fill","hd":false},{"ty":"st","c":{"a":0,"k":[0.056378315944,0.552941176471,0.184900530647,1],"ix":3},"o":{"a":0,"k":100,"ix":4},"w":{"a":0,"k":14,"ix":5},"lc":1,"lj":1,"ml":4,"bm":0,"nm":"Stroke 1","mn":"ADBE Vector Graphic - Stroke","hd":false},{"ty":"tr","p":{"a":0,"k":[0,0],"ix":2},"a":{"a":0,"k":[0,0],"ix":1},"s":{"a":0,"k":[100,100],"ix":3},"r":{"a":0,"k":0,"ix":6},"o":{"a":0,"k":100,"ix":7},"sk":{"a":0,"k":0,"ix":4},"sa":{"a":0,"k":0,"ix":5},"nm":"Transform"}],"nm":"Group 1","np":3,"cix":2,"bm":0,"ix":1,"mn":"ADBE Vector Group","hd":false}],"ip":0,"op":57,"st":0,"bm":0},{"ddd":0,"ind":7,"ty":4,"nm":"Palm Line 2","parent":2,"sr":1,"ks":{"o":{"a":0,"k":100,"ix":11},"r":{"a":0,"k":0,"ix":10},"p":{"a":0,"k":[260.156,6.357,0],"ix":2},"a":{"a":0,"k":[0,0,0],"ix":1},"s":{"a":0,"k":[100,100,100],"ix":6}},"ao":0,"shapes":[{"ty":"gr","it":[{"ind":0,"ty":"sh","ix":1,"ks":{"a":0,"k":{"i":[[148.547,-45.717],[2.93,-102.258],[-106.906,-10.678],[106.411,37.043]],"o":[[-46.441,14.292],[-2.93,102.258],[149.725,14.955],[-143.697,-50.023]],"v":[[-83.714,-179.063],[-212.657,-28.699],[-27.63,188.562],[224.684,-8.58]],"c":true},"ix":2},"nm":"Path 1","mn":"ADBE Vector Shape - Group","hd":false},{"ty":"st","c":{"a":0,"k":[0.317647069693,0.180392161012,0.113725490868,1],"ix":3},"o":{"a":0,"k":100,"ix":4},"w":{"a":0,"k":5,"ix":5},"lc":2,"lj":1,"ml":10,"bm":0,"nm":"Stroke 1","mn":"ADBE Vector Graphic - Stroke","hd":false},{"ty":"tr","p":{"a":0,"k":[0,0],"ix":2},"a":{"a":0,"k":[0,0],"ix":1},"s":{"a":0,"k":[100,100],"ix":3},"r":{"a":0,"k":0,"ix":6},"o":{"a":0,"k":100,"ix":7},"sk":{"a":0,"k":0,"ix":4},"sa":{"a":0,"k":0,"ix":5},"nm":"Transform"}],"nm":"Group 1","np":3,"cix":2,"bm":0,"ix":1,"mn":"ADBE Vector Group","hd":false},{"ty":"tm","s":{"a":0,"k":99,"ix":1},"e":{"a":0,"k":92.5,"ix":2},"o":{"a":0,"k":-71,"ix":3},"m":1,"ix":2,"nm":"Trim Paths 1","mn":"ADBE Vector Filter - Trim","hd":false}],"ip":0,"op":57,"st":0,"bm":0},{"ddd":0,"ind":8,"ty":4,"nm":"Palm Line","parent":2,"sr":1,"ks":{"o":{"a":0,"k":100,"ix":11},"r":{"a":0,"k":0,"ix":10},"p":{"a":0,"k":[260.156,6.357,0],"ix":2},"a":{"a":0,"k":[0,0,0],"ix":1},"s":{"a":0,"k":[100,100,100],"ix":6}},"ao":0,"shapes":[{"ty":"gr","it":[{"ind":0,"ty":"sh","ix":1,"ks":{"a":0,"k":{"i":[[148.547,-45.717],[2.93,-102.258],[-106.906,-10.678],[106.411,37.043]],"o":[[-46.441,14.292],[-2.93,102.258],[149.725,14.955],[-143.697,-50.023]],"v":[[-83.714,-179.063],[-212.657,-28.699],[-27.63,188.562],[224.684,-8.58]],"c":true},"ix":2},"nm":"Path 1","mn":"ADBE Vector Shape - Group","hd":false},{"ty":"st","c":{"a":0,"k":[0.317647069693,0.180392161012,0.113725490868,1],"ix":3},"o":{"a":0,"k":100,"ix":4},"w":{"a":0,"k":6,"ix":5},"lc":2,"lj":1,"ml":10,"bm":0,"nm":"Stroke 1","mn":"ADBE Vector Graphic - Stroke","hd":false},{"ty":"tr","p":{"a":0,"k":[0,0],"ix":2},"a":{"a":0,"k":[0,0],"ix":1},"s":{"a":0,"k":[100,100],"ix":3},"r":{"a":0,"k":0,"ix":6},"o":{"a":0,"k":100,"ix":7},"sk":{"a":0,"k":0,"ix":4},"sa":{"a":0,"k":0,"ix":5},"nm":"Transform"}],"nm":"Group 1","np":3,"cix":2,"bm":0,"ix":1,"mn":"ADBE Vector Group","hd":false},{"ty":"tm","s":{"a":0,"k":17,"ix":1},"e":{"a":0,"k":76,"ix":2},"o":{"a":0,"k":-71,"ix":3},"m":1,"ix":2,"nm":"Trim Paths 1","mn":"ADBE Vector Filter - Trim","hd":false}],"ip":0,"op":57,"st":0,"bm":0},{"ddd":0,"ind":9,"ty":4,"nm":"Palm","parent":2,"sr":1,"ks":{"o":{"a":0,"k":100,"ix":11},"r":{"a":0,"k":0,"ix":10},"p":{"a":0,"k":[260.156,6.357,0],"ix":2},"a":{"a":0,"k":[0,0,0],"ix":1},"s":{"a":0,"k":[100,100,100],"ix":6}},"ao":0,"shapes":[{"ty":"gr","it":[{"ind":0,"ty":"sh","ix":1,"ks":{"a":0,"k":{"i":[[148.547,-45.717],[2.93,-102.258],[-106.906,-10.678],[106.411,37.043]],"o":[[-46.441,14.292],[-2.93,102.258],[149.725,14.955],[-143.697,-50.023]],"v":[[-83.714,-179.063],[-212.657,-28.699],[-27.63,188.562],[224.684,-8.58]],"c":true},"ix":2},"nm":"Path 1","mn":"ADBE Vector Shape - Group","hd":false},{"ty":"fl","c":{"a":0,"k":[0.600000023842,0.372549027205,0.247058823705,1],"ix":4},"o":{"a":0,"k":100,"ix":5},"r":1,"bm":0,"nm":"Fill 1","mn":"ADBE Vector Graphic - Fill","hd":false},{"ty":"tr","p":{"a":0,"k":[0,0],"ix":2},"a":{"a":0,"k":[0,0],"ix":1},"s":{"a":0,"k":[100,100],"ix":3},"r":{"a":0,"k":0,"ix":6},"o":{"a":0,"k":100,"ix":7},"sk":{"a":0,"k":0,"ix":4},"sa":{"a":0,"k":0,"ix":5},"nm":"Transform"}],"nm":"Group 1","np":3,"cix":2,"bm":0,"ix":1,"mn":"ADBE Vector Group","hd":false}],"ip":0,"op":57,"st":0,"bm":0},{"ddd":0,"ind":10,"ty":4,"nm":"MIddle Fin","parent":2,"sr":1,"ks":{"o":{"a":0,"k":100,"ix":11},"r":{"a":0,"k":0,"ix":10},"p":{"a":0,"k":[580.227,59.93,0],"ix":2},"a":{"a":0,"k":[0,0,0],"ix":1},"s":{"a":0,"k":[100,100,100],"ix":6}},"ao":0,"shapes":[{"ty":"gr","it":[{"ind":0,"ty":"sh","ix":1,"ks":{"a":1,"k":[{"i":{"x":0.4,"y":1},"o":{"x":0.6,"y":0},"t":11,"s":[{"i":[[4.71,24.122],[28.8,-2.603],[58.702,-33.277],[18.62,4.232],[-21.6,-43.124],[-48.73,16.126],[-23.495,11.299]],"o":[[-6.275,-32.14],[-28.8,2.603],[-58.702,33.277],[-38.9,-8.841],[22.209,44.34],[48.73,-16.126],[23.495,-11.299]],"v":[[212.925,-60.861],[140.762,-103.881],[-18.463,-38.078],[-148.354,7.717],[-208.248,82.034],[6.012,77.037],[184.341,0.968]],"c":true}]},{"i":{"x":0.4,"y":1},"o":{"x":0.6,"y":0},"t":21,"s":[{"i":[[7.039,23.548],[28.409,-5.398],[64.403,-13.041],[18.201,5.775],[-24.871,-45.849],[-50.493,9.224],[-22.281,13.535]],"o":[[-9.379,-31.375],[-28.409,5.398],[-66.135,13.392],[-49.186,-15.607],[23.646,43.591],[50.493,-9.224],[22.281,-13.535]],"v":[[215.075,-26.167],[139.062,-61.947],[-11.63,-8.889],[-161.952,-0.351],[-232.23,76.981],[-15.497,110.311],[192.655,38.155]],"c":true}]},{"i":{"x":0.833,"y":0.833},"o":{"x":0.6,"y":0},"t":28,"s":[{"i":[[22.543,9.792],[14.179,-25.202],[45.639,-47.274],[19.09,-0.454],[-38.422,-35.277],[-36.692,35.893],[-4.59,76.568]],"o":[[-30.035,-13.047],[-14.179,25.202],[-46.867,48.546],[-51.588,1.226],[36.53,33.539],[62.438,-61.08],[1.56,-26.024]],"v":[[112.461,-240.961],[36.117,-205.893],[-30.453,-63.258],[-181.486,0.007],[-222.814,95.982],[39.513,13.098],[147.199,-182.368]],"c":true}]},{"i":{"x":0.4,"y":1},"o":{"x":0.167,"y":0.167},"t":36,"s":[{"i":[[18.113,13.722],[18.245,-19.544],[51,-37.493],[18.836,1.326],[-34.55,-38.298],[-40.635,28.274],[-9.645,58.559]],"o":[[-24.134,-18.283],[-18.245,19.544],[-52.372,38.502],[-50.902,-3.584],[32.849,36.411],[59.025,-46.264],[7.48,-22.456]],"v":[[141.779,-179.592],[65.53,-164.765],[-25.075,-47.724],[-175.905,-0.095],[-225.504,90.553],[23.796,40.873],[160.186,-119.362]],"c":true}]},{"t":45,"s":[{"i":[[4.71,24.122],[28.8,-2.603],[58.702,-33.277],[18.62,4.232],[-21.6,-43.124],[-48.73,16.126],[-23.495,11.299]],"o":[[-6.275,-32.14],[-28.8,2.603],[-58.702,33.277],[-38.9,-8.841],[22.209,44.34],[48.73,-16.126],[23.495,-11.299]],"v":[[212.925,-60.861],[140.762,-103.881],[-18.463,-38.078],[-148.354,7.717],[-208.248,82.034],[6.012,77.037],[184.341,0.968]],"c":true}]}],"ix":2},"nm":"Path 1","mn":"ADBE Vector Shape - Group","hd":false},{"ty":"st","c":{"a":0,"k":[0.317647069693,0.180392161012,0.113725490868,1],"ix":3},"o":{"a":0,"k":100,"ix":4},"w":{"a":0,"k":5,"ix":5},"lc":2,"lj":1,"ml":10,"bm":0,"nm":"Stroke 1","mn":"ADBE Vector Graphic - Stroke","hd":false},{"ty":"fl","c":{"a":0,"k":[0.600000023842,0.372549027205,0.247058823705,1],"ix":4},"o":{"a":0,"k":100,"ix":5},"r":1,"bm":0,"nm":"Fill 1","mn":"ADBE Vector Graphic - Fill","hd":false},{"ty":"tr","p":{"a":0,"k":[0,0],"ix":2},"a":{"a":0,"k":[0,0],"ix":1},"s":{"a":0,"k":[100,100],"ix":3},"r":{"a":0,"k":0,"ix":6},"o":{"a":0,"k":100,"ix":7},"sk":{"a":0,"k":0,"ix":4},"sa":{"a":0,"k":0,"ix":5},"nm":"Transform"}],"nm":"Group 1","np":3,"cix":2,"bm":0,"ix":1,"mn":"ADBE Vector Group","hd":false}],"ip":0,"op":57,"st":0,"bm":0},{"ddd":0,"ind":11,"ty":4,"nm":"Index Fin","parent":2,"sr":1,"ks":{"o":{"a":0,"k":100,"ix":11},"r":{"a":0,"k":0,"ix":10},"p":{"a":0,"k":[591.165,-4.491,0],"ix":2},"a":{"a":0,"k":[0,0,0],"ix":1},"s":{"a":0,"k":[100,100,100],"ix":6}},"ao":0,"shapes":[{"ty":"gr","it":[{"ind":0,"ty":"sh","ix":1,"ks":{"a":1,"k":[{"i":{"x":0.4,"y":1},"o":{"x":0.6,"y":0},"t":12,"s":[{"i":[[-23.354,-22.191],[29.245,-21.979],[36.804,54.369],[-52.604,3.967],[-35.24,47.858]],"o":[[22.361,21.247],[-29.245,21.979],[-36,-53.182],[61.761,-4.657],[20.501,-27.842]],"v":[[157.864,-92.209],[126.414,0.659],[-154.386,95.775],[-87.385,-3.706],[76.403,-88.558]],"c":true}]},{"i":{"x":0.4,"y":1},"o":{"x":0.6,"y":0},"t":22,"s":[{"i":[[-20.361,-24.966],[31.789,-18.105],[29.634,58.586],[-52.683,-2.717],[-41.008,43.018]],"o":[[19.495,23.904],[-31.789,18.105],[-28.987,-57.307],[61.855,3.189],[23.857,-25.026]],"v":[[167.929,-55.385],[124.99,32.761],[-165.583,91.609],[-86.541,1.398],[86.661,-62.064]],"c":true}]},{"i":{"x":0.833,"y":0.833},"o":{"x":0.6,"y":0},"t":28,"s":[{"i":[[-32.468,0.667],[7.606,-45.526],[47.525,45.297],[-50.553,15.076],[3.854,59.308]],"o":[[40.86,-0.839],[-19.916,119.209],[-46.488,-44.308],[26.167,-7.804],[-2.866,-44.098]],"v":[[-24.016,-168.901],[21.666,-59.32],[-154.81,77.324],[-108.309,-15.133],[-77.046,-102.42]],"c":true}]},{"i":{"x":0.4,"y":1},"o":{"x":0.167,"y":0.167},"t":37,"s":[{"i":[[-22.649,-23.057],[29.043,-27.626],[41.562,49.727],[-52.589,2.244],[-39.323,44.535]],"o":[[26.46,26.512],[-51.006,53.332],[-40.654,-48.641],[66.865,-3.096],[27.027,-30.794]],"v":[[144.76,-95.775],[112.22,-2.948],[-157.086,93.825],[-101.199,-10.549],[61.443,-90.746]],"c":true}]},{"t":44,"s":[{"i":[[-23.354,-22.191],[29.245,-21.979],[36.804,54.369],[-52.604,3.967],[-35.24,47.858]],"o":[[22.361,21.247],[-29.245,21.979],[-36,-53.182],[61.761,-4.657],[20.501,-27.842]],"v":[[157.864,-92.209],[126.414,0.659],[-154.386,95.775],[-87.385,-3.706],[76.403,-88.558]],"c":true}]}],"ix":2},"nm":"Path 1","mn":"ADBE Vector Shape - Group","hd":false},{"ty":"st","c":{"a":0,"k":[0.317647069693,0.180392161012,0.113725490868,1],"ix":3},"o":{"a":0,"k":100,"ix":4},"w":{"a":0,"k":5,"ix":5},"lc":2,"lj":1,"ml":10,"bm":0,"nm":"Stroke 1","mn":"ADBE Vector Graphic - Stroke","hd":false},{"ty":"fl","c":{"a":0,"k":[0.600000023842,0.372549027205,0.247058823705,1],"ix":4},"o":{"a":0,"k":100,"ix":5},"r":1,"bm":0,"nm":"Fill 1","mn":"ADBE Vector Graphic - Fill","hd":false},{"ty":"tr","p":{"a":0,"k":[0,0],"ix":2},"a":{"a":0,"k":[0,0],"ix":1},"s":{"a":0,"k":[100,100],"ix":3},"r":{"a":0,"k":0,"ix":6},"o":{"a":0,"k":100,"ix":7},"sk":{"a":0,"k":0,"ix":4},"sa":{"a":0,"k":0,"ix":5},"nm":"Transform"}],"nm":"Group 1","np":3,"cix":2,"bm":0,"ix":1,"mn":"ADBE Vector Group","hd":false}],"ip":0,"op":57,"st":0,"bm":0},{"ddd":0,"ind":12,"ty":4,"nm":"Thumb","parent":2,"sr":1,"ks":{"o":{"a":0,"k":100,"ix":11},"r":{"a":0,"k":0,"ix":10},"p":{"a":0,"k":[316.243,-131.404,0],"ix":2},"a":{"a":0,"k":[0,0,0],"ix":1},"s":{"a":0,"k":[100,100,100],"ix":6}},"ao":0,"shapes":[{"ty":"gr","it":[{"ind":0,"ty":"sh","ix":1,"ks":{"a":1,"k":[{"i":{"x":0.4,"y":1},"o":{"x":0.6,"y":0},"t":12,"s":[{"i":[[-24.505,1.949],[8.598,-68.748],[9.016,-11.413],[-33.211,-71.865],[85.263,58.358],[-20.842,39.032],[-17.079,2.891],[-19.976,75.992]],"o":[[29.362,-2.335],[-8.598,68.748],[-9.016,11.413],[33.211,71.865],[-85.263,-58.358],[20.842,-39.032],[17.079,-2.891],[8.271,-31.463]],"v":[[105.251,-212.596],[170.439,-115.365],[95.064,-7],[93.387,111.791],[-92.433,190.098],[-161.022,-8.091],[-82.986,-54.084],[54.112,-157.599]],"c":true}]},{"i":{"x":0.4,"y":1},"o":{"x":0.6,"y":0},"t":25,"s":[{"i":[[-23.844,-20.253],[40.064,-56.525],[11.906,-27.542],[-15.011,-39.951],[85.263,58.358],[-20.842,39.032],[-17.32,-0.271],[-53.56,69.905]],"o":[[22.449,19.068],[-40.064,56.525],[-5.771,13.35],[27.845,74.11],[-85.263,-58.358],[20.842,-39.032],[17.32,0.271],[19.785,-25.824]],"v":[[169.911,-162.049],[173.249,-49.834],[79.918,30.504],[93.387,111.791],[-92.433,190.098],[-161.022,-8.091],[-83.118,-53.711],[91.063,-146.481]],"c":true}]},{"i":{"x":0.833,"y":0.833},"o":{"x":0.6,"y":0},"t":31,"s":[{"i":[[-24.505,1.949],[8.598,-68.748],[9.016,-11.413],[-33.211,-71.865],[85.263,58.358],[-20.842,39.032],[-17.079,2.891],[-19.976,75.992]],"o":[[29.362,-2.335],[-8.598,68.748],[-9.016,11.413],[33.211,71.865],[-85.263,-58.358],[20.842,-39.032],[17.079,-2.891],[8.271,-31.463]],"v":[[105.251,-212.596],[170.439,-115.365],[95.064,-7],[93.387,111.791],[-92.433,190.098],[-161.022,-8.091],[-82.986,-54.084],[54.112,-157.599]],"c":true}]},{"i":{"x":0.4,"y":1},"o":{"x":0.167,"y":0.167},"t":39,"s":[{"i":[[-24.285,-5.452],[19.087,-64.673],[9.979,-16.789],[-27.145,-61.227],[85.263,58.358],[-20.842,39.032],[-17.16,1.837],[-31.171,73.963]],"o":[[27.057,4.8],[-19.087,64.673],[-7.934,12.058],[31.423,72.613],[-85.263,-58.358],[20.842,-39.032],[17.16,-1.837],[12.109,-29.583]],"v":[[126.804,-195.747],[171.376,-93.521],[90.015,5.501],[93.387,111.791],[-92.433,190.098],[-161.022,-8.091],[-83.03,-53.96],[66.429,-153.893]],"c":true}]},{"t":43,"s":[{"i":[[-24.505,1.949],[8.598,-68.748],[9.016,-11.413],[-33.211,-71.865],[85.263,58.358],[-20.842,39.032],[-17.079,2.891],[-19.976,75.992]],"o":[[29.362,-2.335],[-8.598,68.748],[-9.016,11.413],[33.211,71.865],[-85.263,-58.358],[20.842,-39.032],[17.079,-2.891],[8.271,-31.463]],"v":[[105.251,-212.596],[170.439,-115.365],[95.064,-7],[93.387,111.791],[-92.433,190.098],[-161.022,-8.091],[-82.986,-54.084],[54.112,-157.599]],"c":true}]}],"ix":2},"nm":"Path 1","mn":"ADBE Vector Shape - Group","hd":false},{"ty":"st","c":{"a":0,"k":[0.317647069693,0.180392161012,0.113725490868,1],"ix":3},"o":{"a":0,"k":100,"ix":4},"w":{"a":0,"k":5,"ix":5},"lc":2,"lj":1,"ml":10,"bm":0,"nm":"Stroke 1","mn":"ADBE Vector Graphic - Stroke","hd":false},{"ty":"fl","c":{"a":0,"k":[0.600000023842,0.372549027205,0.247058823705,1],"ix":4},"o":{"a":0,"k":100,"ix":5},"r":1,"bm":0,"nm":"Fill 1","mn":"ADBE Vector Graphic - Fill","hd":false},{"ty":"tr","p":{"a":0,"k":[0,0],"ix":2},"a":{"a":0,"k":[0,0],"ix":1},"s":{"a":0,"k":[100,100],"ix":3},"r":{"a":0,"k":0,"ix":6},"o":{"a":0,"k":100,"ix":7},"sk":{"a":0,"k":0,"ix":4},"sa":{"a":0,"k":0,"ix":5},"nm":"Transform"}],"nm":"Group 1","np":3,"cix":2,"bm":0,"ix":1,"mn":"ADBE Vector Group","hd":false}],"ip":0,"op":57,"st":0,"bm":0}],"markers":[]}